{
  "main": {
    "id": "f6eab80bf36c296d",
    "type": "split",
    "children": [
      {
        "id": "79c897598b0c83ef",
        "type": "tabs",
        "children": [
          {
            "id": "b33c9735c0eb82a8",
            "type": "leaf",
            "state": {
              "type": "markdown",
              "state": {
                "file": "README.md",
                "mode": "source",
                "source": false
              },
              "icon": "lucide-file",
              "title": "README"
            }
          },
          {
            "id": "548ba6efc9b30994",
            "type": "leaf",
            "state": {
              "type": "graph",
              "state": {},
              "icon": "lucide-git-fork",
              "title": "Graph view"
            }
          }
        ],
        "currentTab": 1
      }
    ],
    "direction": "vertical"
  },
  "left": {
    "id": "41f8fa4feb7a8fac",
    "type": "split",
    "children": [
      {
        "id": "c23e0e17c56d073d",
        "type": "tabs",
        "children": [
          {
            "id": "f585f9b0d07b1a74",
            "type": "leaf",
            "state": {
              "type": "file-explorer",
              "state": {
                "sortOrder": "alphabetical",
                "autoReveal": false
              },
              "icon": "lucide-folder-closed",
              "title": "Files"
            }
          },
          {
            "id": "f575d66bc0cc0dae",
            "type": "leaf",
            "state": {
              "type": "search",
              "state": {
                "query": "tag:#devops",
                "matchingCase": false,
                "explainSearch": false,
                "collapseAll": false,
                "extraContext": false,
                "sortOrder": "alphabetical"
              },
              "icon": "lucide-search",
              "title": "Search"
            }
          },
          {
            "id": "2430a0d57c0d4f3b",
            "type": "leaf",
            "state": {
              "type": "bookmarks",
              "state": {},
              "icon": "lucide-bookmark",
              "title": "Bookmarks"
            }
          }
        ]
      }
    ],
    "direction": "horizontal",
    "width": 300
  },
  "right": {
    "id": "3767cfcc003e6e5e",
    "type": "split",
    "children": [
      {
        "id": "af19308f31106c35",
        "type": "tabs",
        "children": [
          {
            "id": "6c2ce6c30263b8c5",
            "type": "leaf",
            "state": {
              "type": "backlink",
              "state": {
                "file": "mcp/mcp-graphiti/README.md",
                "collapseAll": false,
                "extraContext": false,
                "sortOrder": "alphabetical",
                "showSearch": false,
                "searchQuery": "",
                "backlinkCollapsed": false,
                "unlinkedCollapsed": true
              },
              "icon": "links-coming-in",
              "title": "Backlinks for README"
            }
          },
          {
            "id": "d25d3490f051e49a",
            "type": "leaf",
            "state": {
              "type": "outgoing-link",
              "state": {
                "file": "CIA and Mossad.md",
                "linksCollapsed": false,
                "unlinkedCollapsed": true
              },
              "icon": "links-going-out",
              "title": "Outgoing links from CIA and Mossad"
            }
          },
          {
            "id": "b0a7895e37d62fa1",
            "type": "leaf",
            "state": {
              "type": "tag",
              "state": {
                "sortOrder": "frequency",
                "useHierarchy": true,
                "showSearch": false,
                "searchQuery": ""
              },
              "icon": "lucide-tags",
              "title": "Tags"
            }
          },
          {
            "id": "dfec9d8f82e4bb72",
            "type": "leaf",
            "state": {
              "type": "outline",
              "state": {
                "file": "mcp/mcp-graphiti/README.md",
                "followCursor": false,
                "showSearch": false,
                "searchQuery": ""
              },
              "icon": "lucide-list",
              "title": "Outline of README"
            }
          },
          {
            "id": "81457d22d3b3c2b8",
            "type": "leaf",
            "state": {
              "type": "smart-connections-view",
              "state": {},
              "icon": "smart-connections",
              "title": "Connections"
            }
          }
        ],
        "currentTab": 4
      }
    ],
    "direction": "horizontal",
    "width": 434.5
  },
  "left-ribbon": {
    "hiddenItems": {
      "switcher:Open quick switcher": false,
      "graph:Open graph view": false,
      "canvas:Create new canvas": false,
      "daily-notes:Open today's daily note": false,
      "templates:Insert template": false,
      "command-palette:Open command palette": false,
      "bases:Create new base": false,
      "smart-connections:Open: Smart Chat": false,
      "smart-connections:Smart Connections: Open connections view": false,
      "smart-connections:Smart Connections: Open random connection": false
    }
  },
  "active": "548ba6efc9b30994",
  "lastOpenFiles": [
    "_system/processing-pipeline-protocol.md.tmp.71860.1762847481526",
    "scripts/monthly_consolidation.py",
    "scripts/monthly_consolidation.py.tmp.71860.1762847459459",
    "_system/processing-pipeline-protocol.md.tmp.71860.1762847397857",
    "_system/processing-pipeline-protocol.md.tmp.71860.1762847315164",
    "_system/processing-pipeline-protocol.md.tmp.71860.1762847262546",
    "_system/processing-pipeline-protocol.md.tmp.71860.1762847232068",
    "_system/tag-note-template.md",
    "_system/tag-note-template.md.tmp.71860.1762847219178",
    "_system/tag-taxonomy.md.tmp.71860.1762847194604",
    "_system/tag-taxonomy.md.tmp.71860.1762847165729",
    "_system/tag-taxonomy.md.tmp.71860.1762847141821",
    "planning/merge-plan.md",
    "Untitled 1.canvas",
    "Untitled.canvas",
    "2025-11-10.md",
    "00-Inbox/processed/conversation_20251109_neo4j_mcp_integration.md",
    "60-Jots/Titles for the empire.md",
    "README.md",
    "Financial Markets.md",
    "Tag Review Queue.md",
    "_system/CRITICAL_FIX_APPLIED.md",
    "00-Inbox/raw-conversations/processed_test_pipeline_20251109_001.md",
    "00-Inbox/processed/conversation_20251109_neo4j_fastapi_integration.md",
    "_system/SETUP_COMPLETION_SUMMARY.md",
    "00-Inbox/raw-conversations/processing_test_pipeline_20251109_001.md",
    "00-Inbox/raw-conversations/unprocessed_test_pipeline_20251109_001.md",
    "_system/mcp-tools-reference.md",
    "mcp/mcp-graphiti/README.md",
    "mcp/mcp-graphiti/ai/graph/meta-graph-draft.md",
    "00-Inbox/processed/conversation_20251109_test_pipeline_001.md",
    "Neo4j.md",
    "00-Inbox/raw-conversations/processed_test_realtime_002.md",
    "00-Inbox/processed/conversation_20251109_ml_classification_pipeline.md",
    "00-Inbox/raw-conversations/processing_test_realtime_002.md",
    "00-Inbox/raw-conversations/unprocessed_test_realtime_002.md",
    "_system/SETUP_COMPLETE_README.md",
    "_system/COMPLETE_PROCESSING_ARCHITECTURE.md",
    "Excalidraw/Untitled.canvas"
  ]
}